torrch/__init__.py
torrch-0.0.6.dist-info/METADATA
torrch-0.0.6.dist-info/WHEEL
torrch-0.0.6.dist-info/top_level.txt
torrch-0.0.6.dist-info/RECORD
