Metadata-Version: 2.1
Name: torrch
Version: 0.0.6
Summary: This is the simplest module for quick work with files.
Home-page: https://github.com/vadlord
Author: dudadu
Author-email: 89084961059v@gmail.com
Project-URL: GitHub, https://github.com/vadlord
Keywords: files speedfiles
Classifier: Programming Language :: Python :: 3.11
Classifier: License :: OSI Approved :: MIT License
Classifier: Operating System :: OS Independent
Requires-Python: >=3.6
Requires-Dist: requests >=2.25.1
